{
  "slug": "triangle-of-wellness-xtreme",
  "name": "Triangle of Wellness Xtreme™",
  "nameNL": "Triangle of Wellness Xtreme™",
  "shortNameNL": "Triangle of Wellness Xtreme™",
  "category": "essentials",
  "taglineNL": "Dagelijkse basisondersteuning",
  "description": {
    "short": "Dagelijkse basisondersteuning",
    "long": "Triangle of Wellness Xtreme™ is een premium supplement van Amare, wetenschappelijk onderbouwd en gemaakt met natuurlijke ingrediënten."
  },
  "pricing": {
    "subscription": 123.55,
    "oneTime": 137.27,
    "currency": "EUR",
    "savings": 13.72,
    "savingsPercent": 10
  },
  "images": {
    "primary": "https://amarecdn.azureedge.net/webassets/web/prod/products/Triangle-of-Wellness-Xtreme2-EU-800_25.jpg",
    "alt": "Triangle of Wellness Xtreme™ — Amare supplement"
  },
  "benefits": [
    "Hoogwaardige ingrediënten",
    "Wetenschappelijk onderbouwd",
    "gemaakt met natuurlijke ingrediënten"
  ],
  "usage": {
    "dosage": "Raadpleeg de verpakking voor de aanbevolen dosering.",
    "timing": "Raadpleeg de verpakking",
    "duration": "Eerste effecten na 3-4 weken consistent gebruik"
  },
  "affiliate": {
    "url": "https://www.amare.com/2075008/nl-nl/triangle-of-wellness-xtreme",
    "sourceTag": "amarenl-product-page"
  },
  "relatedProducts": [],
  "tags": [],
  "seo": {
    "title": "Triangle of Wellness Xtreme™ Kopen | Beste Prijs Nederland 2026",
    "description": "Dagelijkse basisondersteuning",
    "keywords": []
  },
  "isNew": false,
  "isBestseller": false,
  "isPack": true,
  "priority": 19,
  "publishedAt": "2024-01-15",
  "updatedAt": "2026-05-17"
}